aznlp/__init__.py
aznlp/corpus/__init__.py
aznlp/tokenize/__init__.py
aznlp-1.1.1.dist-info/LICENSE
aznlp-1.1.1.dist-info/METADATA
aznlp-1.1.1.dist-info/WHEEL
aznlp-1.1.1.dist-info/top_level.txt
aznlp-1.1.1.dist-info/RECORD
