Metadata-Version: 2.1
Name: aznlp
Version: 1.1.1
Summary: 🇦🇿 AZNLP - Natural Language Processing (NLP) library for Azerbaijani Language
Home-page: https://github.com/tifosiai/aznlp
Author: Tifosi AI
Author-email: abdullahkazimov@icloud.com
Classifier: Programming Language :: Python :: 3
Classifier: License :: OSI Approved :: MIT License
Classifier: Operating System :: OS Independent
Requires-Python: >=3.6
License-File: LICENSE
